atomicpay/__init__.py
atomicpay/models.py
atomicpay/utils.py
atomicpay/equity/__init__.py
atomicpay/equity/api.py
atomicpay/equity/auth.py
atomicpay/equity/client.py
atomicpay/equity/exceptions.py
atomicpay/equity/models.py
atomicpay/equity/routes.py
atomicpay/helpers/__init__.py
atomicpay/helpers/singleton.py
atomicpay/mpesa/__init__.py
atomicpay/mpesa/api.py
atomicpay/mpesa/auth.py
atomicpay/mpesa/b2b.py
atomicpay/mpesa/b2c.py
atomicpay/mpesa/c2b.py
atomicpay/mpesa/client.py
atomicpay/mpesa/exceptions.py
atomicpay/mpesa/lipa.py
atomicpay/mpesa/models.py
atomicpay/mpesa/routes.py
atomicpay-0.1.4.dist-info/DESCRIPTION.rst
atomicpay-0.1.4.dist-info/METADATA
atomicpay-0.1.4.dist-info/RECORD
atomicpay-0.1.4.dist-info/WHEEL
atomicpay-0.1.4.dist-info/metadata.json
atomicpay-0.1.4.dist-info/top_level.txt
