Metadata-Version: 2.0
Name: atomicpay
Version: 0.1.4
Summary: Simplified Payments
Home-page: https://github.com/mainanick/atomicpay
Author: Nick Maina
Author-email: nick.maina1@gmail.com
License: MIT
Requires-Dist: requests
Provides-Extra: dev
Requires-Dist: Flask; extra == 'dev'
Provides-Extra: test
Requires-Dist: coverage; extra == 'test'
